neer_match_utilities/__init__.py
neer_match_utilities/base.py
neer_match_utilities/custom_similarities.py
neer_match_utilities/model.py
neer_match_utilities/panel.py
neer_match_utilities/prepare.py
neer_match_utilities/split.py
neer_match_utilities/training.py
neer_match_utilities-1.0.26b0.dist-info/licenses/LICENSE.txt
neer_match_utilities-1.0.26b0.dist-info/METADATA
neer_match_utilities-1.0.26b0.dist-info/WHEEL
neer_match_utilities-1.0.26b0.dist-info/top_level.txt
neer_match_utilities-1.0.26b0.dist-info/RECORD
