Metadata-Version: 2.4
Name: neer-match-utilities
Version: 1.0.26b0
Summary: Extended funcationality for NEural-symbolic Entity Reasoning and Matching
Author-email: Marius Liebald <maliedvp@gmail.com>, Pantelis Karapanagiotis <pikappa.devel@gmail.com>
Project-URL: Homepage, https://www.marius-liebald.com/py-neer-utilities/
Project-URL: Documentation, https://www.marius-liebald.com/py-neer-utilities/
Project-URL: Source Code, https://github.com/maliedvp/py-neer-utilities
Project-URL: Bug Tracker, https://github.com/maliedvp/py-neer-utilities/issues
Classifier: Environment :: Console
Classifier: Intended Audience :: Developers
Classifier: Intended Audience :: Information Technology
Classifier: Intended Audience :: Science/Research
Classifier: License :: OSI Approved :: MIT License
Classifier: Operating System :: OS Independent
Classifier: Programming Language :: Python :: 3
Classifier: Topic :: Database
Classifier: Topic :: Scientific/Engineering :: Artificial Intelligence
Requires-Python: <3.13,>=3.10
License-File: LICENSE.txt
Requires-Dist: ltn>=0.0.1
Requires-Dist: matplotlib>=3.5.0
Requires-Dist: numpy>=1.26.4
Requires-Dist: pandas>=2.2.3
Requires-Dist: rapidfuzz>=3.10.1
Requires-Dist: tensorflow>=2.18.0
Requires-Dist: neer-match>=0.7.38
Requires-Dist: dill>=0.3.8
Requires-Dist: spacy>=3.8.7
Requires-Dist: pydot>=4.0.1
Requires-Dist: graphviz>=0.21
Provides-Extra: tests
Requires-Dist: pytest; extra == "tests"
Dynamic: license-file
